autopyproject/__main__.py
autopyproject/autopyproject.py
autopyproject-0.1.1.dist-info/METADATA
autopyproject-0.1.1.dist-info/WHEEL
autopyproject-0.1.1.dist-info/entry_points.txt
autopyproject-0.1.1.dist-info/top_level.txt
autopyproject-0.1.1.dist-info/RECORD
