Metadata-Version: 2.4
Name: autopyproject
Version: 0.1.1
Summary: Python project scaffolder
Author: Ismail Farooq
License-Expression: MIT
Requires-Python: >=3.10
